Metadata-Version: 2.1
Name: bota
Version: 4.0.12
Summary: CLI for botasaurus.
Home-page: https://github.com/omkarcloud/botasaurus-proxy-authentication
Author: Chetan Jain
Author-email: chetan@omkar.cloud
License: MIT
Project-URL: Bug Reports, https://github.com/omkarcloud/botasaurus/issues
Project-URL: Say Thanks!, https://github.com/omkarcloud/botasaurus
Project-URL: Source, https://github.com/omkarcloud/botasaurus/
Keywords: seleniumwire proxy authentication,proxy authentication
Classifier: Development Status :: 5 - Production/Stable
Classifier: Topic :: Software Development :: Testing
Classifier: Topic :: System :: Installation/Setup
Classifier: Topic :: Software Development :: Libraries :: Python Modules
Classifier: License :: OSI Approved :: MIT License
Classifier: Programming Language :: Python :: 3
Classifier: Programming Language :: Python :: 3.6
Classifier: Programming Language :: Python :: 3.7
Classifier: Programming Language :: Python :: 3.8
Classifier: Programming Language :: Python :: 3.9
Classifier: Programming Language :: Python :: 3.10
Requires-Python: >=3.6
License-File: LICENSE
Requires-Dist: click
Provides-Extra: dev
Requires-Dist: check-manifest; extra == "dev"
Provides-Extra: test
Requires-Dist: coverage; extra == "test"
